bibReader/__init__.py
bibReader/_util.py
bibReader/frame.py
bibReader/loader.py
bibReader/parser.py
bibReader/config/config.yaml
bibReader-0.0.8.13.dist-info/LICENSE
bibReader-0.0.8.13.dist-info/METADATA
bibReader-0.0.8.13.dist-info/WHEEL
bibReader-0.0.8.13.dist-info/top_level.txt
bibReader-0.0.8.13.dist-info/RECORD
