Metadata-Version: 2.1
Name: bibReader
Version: 0.0.8.13
Summary: Turns data into panda dataframe
Home-page: https://github.com/jshinm/bibReader/
Author: Jong M. Shin
Author-email: jshinm@gmail.com
License: MIT
Classifier: Programming Language :: Python :: 3
Classifier: License :: OSI Approved :: MIT License
Classifier: Operating System :: OS Independent
Requires: pandas
Requires: requests
Requires: pyyaml
License-File: LICENSE
Requires-Dist: pandas
Requires-Dist: requests
Requires-Dist: pyyaml
